{"inkVersion":17,"root":["done",{"CustomEvent":[{"temp=":"string"},"ev","void","/ev","~ret",{"#f":3}],"WATCHERS":[[{"#":"w:right"},"^Hey psst.","\n","^Do you know much about this film? ",{"#":"w:right"},"\n",["ev",{"^->":"WATCHERS.0.6.$r1"},{"temp=":"$r"},"str",{"->":".^.s"},[{"#n":"$r1"}],"/str","/ev",{"*":".^.c","flg":18},{"s":["^Not at all.",{"->":"$r","var":true},null],"c":["ev",{"^->":"WATCHERS.0.6.c.$r2"},"/ev",{"temp=":"$r"},{"->":".^.^.s"},[{"#n":"$r2"}],"\n","\n",[["ev",{"^->":"WATCHERS.0.6.c.8.0.$r1"},{"temp=":"$r"},"str",{"->":".^.s"},[{"#n":"$r1"}],"/str","/ev",{"*":".^.c","flg":18},{"s":["^I've never heard of it.",{"->":"$r","var":true},null],"c":["ev",{"^->":"WATCHERS.0.6.c.8.0.c.$r2"},"/ev",{"temp=":"$r"},{"->":".^.^.s"},[{"#n":"$r2"}],"\n","\n",{"#":"w:right"},"\n","^I think it's some kind of documentary.","\n",{"#":"w:right"},"\n","^About hotels.","\n",{"#":"w:right"},"\n","^Always found hotels quite spooky.","\n",[["ev",{"^->":"WATCHERS.0.6.c.8.0.c.20.0.$r1"},{"temp=":"$r"},"str",{"->":".^.s"},[{"#n":"$r1"}],"/str","/ev",{"*":".^.c","flg":18},{"s":["^I know what you mean.",{"->":"$r","var":true},null],"c":["ev",{"^->":"WATCHERS.0.6.c.8.0.c.20.0.c.$r2"},"/ev",{"temp=":"$r"},{"->":".^.^.s"},[{"#n":"$r2"}],"\n","\n",{"#":"w:right"},"\n","^Just something not quite right about them.","\n",{"#":"w:right"},"\n","^I don't like how everyone is so anonymous.","\n",{"->":".^.^.^.g-0"},{"#f":7}]}],["ev",{"^->":"WATCHERS.0.6.c.8.0.c.20.1.$r1"},{"temp=":"$r"},"str",{"->":".^.s"},[{"#n":"$r1"}],"/str","/ev",{"*":".^.c","flg":18},{"s":["^It's not a horror film is it?",{"->":"$r","var":true},null],"c":["ev",{"^->":"WATCHERS.0.6.c.8.0.c.20.1.c.$r2"},"/ev",{"temp=":"$r"},{"->":".^.^.s"},[{"#n":"$r2"}],"\n","\n",{"#":"w:right"},"\n","^Oh no no I don't think so.","\n",{"#":"w:right"},"\n","^Just a feeling.","\n",{"#":"w:right"},"\n","^Just a strange feeling about it, that's all.","\n",{"#":"w:right"},"\n","^I don't expect it'll be scary, it's just me getting all nervous.","\n",{"#":"w:right"},"\n","^Haha. Yeah.","\n",{"->":".^.^.^.g-0"},{"#f":7}]}],{"g-0":[{"->":".^.^.^.^.^.g-0"},{"#f":7}]}],{"#f":7}]}],["ev",{"^->":"WATCHERS.0.6.c.8.1.$r1"},{"temp=":"$r"},"str",{"->":".^.s"},[{"#n":"$r1"}],"/str","/ev",{"*":".^.c","flg":18},{"s":["^It looks alright though.",{"->":"$r","var":true},null],"c":["ev",{"^->":"WATCHERS.0.6.c.8.1.c.$r2"},"/ev",{"temp=":"$r"},{"->":".^.^.s"},[{"#n":"$r2"}],"\n","\n",{"#":"w:right"},"\n","^Yeah. Kinda spooky though.","\n",{"#":"w:right"},"\n","^Always found hotels quite spooky.","\n",[["ev",{"^->":"WATCHERS.0.6.c.8.1.c.16.0.$r1"},{"temp=":"$r"},"str",{"->":".^.s"},[{"#n":"$r1"}],"/str","/ev",{"*":".^.c","flg":18},{"s":["^I know what you mean.",{"->":"$r","var":true},null],"c":["ev",{"^->":"WATCHERS.0.6.c.8.1.c.16.0.c.$r2"},"/ev",{"temp=":"$r"},{"->":".^.^.s"},[{"#n":"$r2"}],"\n","\n",{"#":"w:right"},"\n","^Just something not quite right about them.","\n",{"#":"w:right"},"\n","^I don't like how everyone is so anonymous.","\n",{"->":".^.^.^.g-0"},{"#f":7}]}],["ev",{"^->":"WATCHERS.0.6.c.8.1.c.16.1.$r1"},{"temp=":"$r"},"str",{"->":".^.s"},[{"#n":"$r1"}],"/str","/ev",{"*":".^.c","flg":18},{"s":["^It's not a horror film is it?",{"->":"$r","var":true},null],"c":["ev",{"^->":"WATCHERS.0.6.c.8.1.c.16.1.c.$r2"},"/ev",{"temp=":"$r"},{"->":".^.^.s"},[{"#n":"$r2"}],"\n","\n",{"#":"w:right"},"\n","^Oh no no I don't think so.","\n",{"#":"w:right"},"\n","^Just a feeling.","\n",{"#":"w:right"},"\n","^Just a strange feeling about it, that's all.","\n",{"#":"w:right"},"\n","^I don't expect it'll be scary, it's just me getting all nervous.","\n",{"#":"w:right"},"\n","^Haha. Yeah.","\n",{"->":".^.^.^.g-0"},{"#f":7}]}],{"g-0":[{"->":".^.^.^.^.^.g-0"},{"#f":7}]}],{"#f":7}]}],["ev",{"^->":"WATCHERS.0.6.c.8.2.$r1"},{"temp=":"$r"},"str",{"->":".^.s"},[{"#n":"$r1"}],"/str","/ev",{"*":".^.c","flg":18},{"s":["^Do you?",{"->":"$r","var":true},null],"c":["ev",{"^->":"WATCHERS.0.6.c.8.2.c.$r2"},"/ev",{"temp=":"$r"},{"->":".^.^.s"},[{"#n":"$r2"}],"\n","\n",{"#":"w:right"},"\n","^Oh no. No idea really.","\n",{"#":"w:right"},"\n","^I think I saw maybe that it was some kind of documentary?","\n",{"#":"w:right"},"\n","^About hotels.","\n",{"#":"w:right"},"\n","^Or, it's based on a true story. One of the two.","\n",{"->":".^.^.^.g-0"},{"#f":7}]}],{"g-0":[{"->":"WATCHERS.0.g-0"},{"#f":7}]}],{"#f":7}]}],["ev",{"^->":"WATCHERS.0.7.$r1"},{"temp=":"$r"},"str",{"->":".^.s"},[{"#n":"$r1"}],"/str","/ev",{"*":".^.c","flg":18},{"s":["^A little bit.",{"->":"$r","var":true},null],"c":["ev",{"^->":"WATCHERS.0.7.c.$r2"},"/ev",{"temp=":"$r"},{"->":".^.^.s"},[{"#n":"$r2"}],"\n","\n",[["ev",{"^->":"WATCHERS.0.7.c.8.0.$r1"},{"temp=":"$r"},"str",{"->":".^.s"},[{"#n":"$r1"}],"/str","/ev",{"*":".^.c","flg":18},{"s":["^It's about hotels, right?",{"->":"$r","var":true},null],"c":["ev",{"^->":"WATCHERS.0.7.c.8.0.c.$r2"},"/ev",{"temp=":"$r"},{"->":".^.^.s"},[{"#n":"$r2"}],"\n","\n",{"->":".^.^.^.g-0"},{"#f":7}]}],["ev",{"^->":"WATCHERS.0.7.c.8.1.$r1"},{"temp=":"$r"},"str",{"->":".^.s"},[{"#n":"$r1"}],"/str","/ev",{"*":".^.c","flg":18},{"s":["^It's about ghosts, right?",{"->":"$r","var":true},null],"c":["ev",{"^->":"WATCHERS.0.7.c.8.1.c.$r2"},"/ev",{"temp=":"$r"},{"->":".^.^.s"},[{"#n":"$r2"}],"\n","\n",{"->":".^.^.^.g-0"},{"#f":7}]}],{"g-0":[{"#":"w:right"},"\n","^Oh is it? I didn't realise.","\n",{"#":"w:right"},"\n","^I thought it was about a car crash? Or something?","\n",{"#":"w:right"},"\n","^As long as it's not boring though.","\n",{"#":"w:right"},"\n","^As long as it's not boring I don't mind.","\n",{"#":"w:right"},"\n","^These kinda things usually are, but I'll keep my fingers crossed.","\n",{"#":"w:right"},"\n","^I'll watch whatever I can nowadays. Nowadays that's all we can do.","\n",{"->":"WATCHERS.0.g-0"},{"#f":7}]}],{"#f":7}]}],{"g-0":[{"#":"w:left"},"^Mmm.","\n",{"#":"w:right"},"^Feels weird though, doesn't it? Sitting out here like this.","\n",["ev",{"^->":"WATCHERS.0.g-0.6.$r1"},{"temp=":"$r"},"str",{"->":".^.s"},[{"#n":"$r1"}],"/str","/ev",{"*":".^.c","flg":18},{"s":["^Yeah. I don't feel safe.",{"->":"$r","var":true},null],"c":["ev",{"^->":"WATCHERS.0.g-0.6.c.$r2"},"/ev",{"temp=":"$r"},{"->":".^.^.s"},[{"#n":"$r2"}],"\n","\n",{"#":"w:right"},"\n","^I'm pretty sure they cautioned off the road.","\n",{"#":"w:right"},"\n","^Like there's no other traffic around.","\n",{"#":"w:right"},"\n","^Plus it's the middle of the night.","\n",[["ev",{"^->":"WATCHERS.0.g-0.6.c.20.0.$r1"},{"temp=":"$r"},"str",{"->":".^.s"},[{"#n":"$r1"}],"/str","/ev",{"*":".^.c","flg":18},{"s":["^Still, a bit creepy.",{"->":"$r","var":true},null],"c":["ev",{"^->":"WATCHERS.0.g-0.6.c.20.0.c.$r2"},"/ev",{"temp=":"$r"},{"->":".^.^.s"},[{"#n":"$r2"}],"\n","\n",{"->":".^.^.^.g-0"},{"#f":7}]}],["ev",{"^->":"WATCHERS.0.g-0.6.c.20.1.$r1"},{"temp=":"$r"},"str",{"->":".^.s"},[{"#n":"$r1"}],"/str","/ev",{"*":".^.c","flg":18},{"s":["^Still, a bit unnerving.",{"->":"$r","var":true},null],"c":["ev",{"^->":"WATCHERS.0.g-0.6.c.20.1.c.$r2"},"/ev",{"temp=":"$r"},{"->":".^.^.s"},[{"#n":"$r2"}],"\n","\n",{"->":".^.^.^.g-0"},{"#f":7}]}],["ev",{"^->":"WATCHERS.0.g-0.6.c.20.2.$r1"},{"temp=":"$r"},"str",{"->":".^.s"},[{"#n":"$r1"}],"/str","/ev",{"*":".^.c","flg":18},{"s":["^Still, a bit eerie.",{"->":"$r","var":true},null],"c":["ev",{"^->":"WATCHERS.0.g-0.6.c.20.2.c.$r2"},"/ev",{"temp=":"$r"},{"->":".^.^.s"},[{"#n":"$r2"}],"\n","\n",{"->":".^.^.^.g-0"},{"#f":7}]}],{"g-0":[{"#":"w:right"},"\n","^Yeah, I know what you mean.","\n",{"#":"w:right"},"\n","^Feels like we're moments away from a disaster.","\n",{"->":"WATCHERS.0.g-1"},{"#f":7}]}],{"#f":7}]}],["ev",{"^->":"WATCHERS.0.g-0.7.$r1"},{"temp=":"$r"},"str",{"->":".^.s"},[{"#n":"$r1"}],"/str","/ev",{"*":".^.c","flg":18},{"s":["^I think it's quite cool.",{"->":"$r","var":true},null],"c":["ev",{"^->":"WATCHERS.0.g-0.7.c.$r2"},"/ev",{"temp=":"$r"},{"->":".^.^.s"},[{"#n":"$r2"}],"\n","\n",{"#":"w:right"},"\n","^It is different that's for sure.","\n",{"#":"w:right"},"\n","^Reminds me of some of that experimental theatre we saw back in the day.","\n",{"#":"w:right"},"\n","^Do you remember that?","\n",[["ev",{"^->":"WATCHERS.0.g-0.7.c.20.0.$r1"},{"temp=":"$r"},"str",{"->":".^.s"},[{"#n":"$r1"}],"/str","/ev",{"*":".^.c","flg":18},{"s":["^Oh, yeah.",{"->":"$r","var":true},null],"c":["ev",{"^->":"WATCHERS.0.g-0.7.c.20.0.c.$r2"},"/ev",{"temp=":"$r"},{"->":".^.^.s"},[{"#n":"$r2"}],"\n","\n",{"->":".^.^.^.g-0"},{"#f":7}]}],["ev",{"^->":"WATCHERS.0.g-0.7.c.20.1.$r1"},{"temp=":"$r"},"str",{"->":".^.s"},[{"#n":"$r1"}],"/str","/ev",{"*":".^.c","flg":18},{"s":["^What, no?",{"->":"$r","var":true},null],"c":["ev",{"^->":"WATCHERS.0.g-0.7.c.20.1.c.$r2"},"/ev",{"temp=":"$r"},{"->":".^.^.s"},[{"#n":"$r2"}],"\n","\n",{"->":".^.^.^.g-0"},{"#f":7}]}],{"g-0":[{"#":"w:right"},"\n","^That ballet in the service station. That weird thing we watched from someone's window overlooking that street.","\n",{"#":"w:right"},"\n","^Maybe it's all by the same artist I'm not sure.","\n",{"->":"WATCHERS.0.g-1"},{"#f":7}]}],{"#f":7}]}],["ev",{"^->":"WATCHERS.0.g-0.8.$r1"},{"temp=":"$r"},"str",{"->":".^.s"},[{"#n":"$r1"}],"/str","/ev",{"*":".^.c","flg":18},{"s":["^What do you mean?",{"->":"$r","var":true},null],"c":["ev",{"^->":"WATCHERS.0.g-0.8.c.$r2"},"/ev",{"temp=":"$r"},{"->":".^.^.s"},[{"#n":"$r2"}],"\n","\n",{"#":"w:right"},"\n","^Like... being just parked up in the middle of the motorway like this.","\n",{"#":"w:right"},"\n","^It's quite frightening. Y'know?","\n",[["ev",{"^->":"WATCHERS.0.g-0.8.c.16.0.$r1"},{"temp=":"$r"},"str",{"->":".^.s"},[{"#n":"$r1"}],"/str","/ev",{"*":".^.c","flg":18},{"s":["^Yeah, exposing.",{"->":"$r","var":true},null],"c":["ev",{"^->":"WATCHERS.0.g-0.8.c.16.0.c.$r2"},"/ev",{"temp=":"$r"},{"->":".^.^.s"},[{"#n":"$r2"}],"\n","\n",{"->":".^.^.^.g-0"},{"#f":7}]}],["ev",{"^->":"WATCHERS.0.g-0.8.c.16.1.$r1"},{"temp=":"$r"},"str",{"->":".^.s"},[{"#n":"$r1"}],"/str","/ev",{"*":".^.c","flg":18},{"s":["^Yeah, eerie.",{"->":"$r","var":true},null],"c":["ev",{"^->":"WATCHERS.0.g-0.8.c.16.1.c.$r2"},"/ev",{"temp=":"$r"},{"->":".^.^.s"},[{"#n":"$r2"}],"\n","\n",{"->":".^.^.^.g-0"},{"#f":7}]}],["ev",{"^->":"WATCHERS.0.g-0.8.c.16.2.$r1"},{"temp=":"$r"},"str",{"->":".^.s"},[{"#n":"$r1"}],"/str","/ev",{"*":".^.c","flg":18},{"s":["^Yeah, exciting.",{"->":"$r","var":true},null],"c":["ev",{"^->":"WATCHERS.0.g-0.8.c.16.2.c.$r2"},"/ev",{"temp=":"$r"},{"->":".^.^.s"},[{"#n":"$r2"}],"\n","\n",{"->":".^.^.^.g-0"},{"#f":7}]}],{"g-0":[{"#":"w:right"},"\n","^Just us and the street lights and the crickets and the night.","\n",{"#":"w:right"},"\n","^And the film of course.","\n",{"->":"WATCHERS.0.g-1"},{"#f":7}]}],{"#f":7}]}],{"#f":7}],"g-1":[{"#":"w:left"},"^Mmm.","\n",{"#":"w:right"},"^Wait shh shh I think it's starting.","\n",["G>","ev","str","^START_MOVIE","/str",{"x()":"CustomEvent","exArgs":1},"out","/ev","G<",null],"\n","done",{"#f":7}]}],{"#f":3}],"WATCHERS_BORED":[[{"#":"w:right"},"^...Hey psst.","\n",{"#":"w:left"},"^What?","\n",{"#":"w:right"},"^Can we talk? I'm kinda bored.","\n",["ev",{"^->":"WATCHERS_BORED.0.9.$r1"},{"temp=":"$r"},"str",{"->":".^.s"},[{"#n":"$r1"}],"/str","/ev",{"*":".^.c","flg":18},{"s":["^Sure. I'm kinda bored too.",{"->":"$r","var":true},null],"c":["ev",{"^->":"WATCHERS_BORED.0.9.c.$r2"},"/ev",{"temp=":"$r"},{"->":".^.^.s"},[{"#n":"$r2"}],"\n","\n",{"#":"w:right"},"^Phew I was worried I was the only one.","\n",{"#":"w:right"},"^I don't get it. Nothing's happening.","\n",[["ev",{"^->":"WATCHERS_BORED.0.9.c.14.0.$r1"},{"temp=":"$r"},"str",{"->":".^.s"},[{"#n":"$r1"}],"/str","/ev",{"*":".^.c","flg":18},{"s":["^Yeah I dunno, I thought it would be better.",{"->":"$r","var":true},null],"c":["ev",{"^->":"WATCHERS_BORED.0.9.c.14.0.c.$r2"},"/ev",{"temp=":"$r"},{"->":".^.^.s"},[{"#n":"$r2"}],"\n","\n",{"#":"w:right"},"\n","^Me too. I guess we should've researched more?","\n",{"#":"w:left"},"\n","^I don't know it's always a risk with these things.","\n",{"->":".^.^.^.g-0"},{"#f":7}]}],["ev",{"^->":"WATCHERS_BORED.0.9.c.14.1.$r1"},{"temp=":"$r"},"str",{"->":".^.s"},[{"#n":"$r1"}],"/str","/ev",{"*":".^.c","flg":18},{"s":["^Maybe that's the point?",{"->":"$r","var":true},null],"c":["ev",{"^->":"WATCHERS_BORED.0.9.c.14.1.c.$r2"},"/ev",{"temp=":"$r"},{"->":".^.^.s"},[{"#n":"$r2"}],"\n","\n",{"#":"w:right"},"\n","^So what though? If the point of it is to be boring, then sure it's succeeded, but I'm still bored.","\n",{"#":"w:left"},"\n","^Yeah I get you.","\n",{"->":".^.^.^.g-0"},{"#f":7}]}],{"g-0":[{"#":"w:right"},"\n","^At least it's a beautiful night.","\n",["ev",{"^->":"WATCHERS_BORED.0.9.c.14.g-0.4.$r1"},{"temp=":"$r"},"str",{"->":".^.s"},[{"#n":"$r1"}],"/str","/ev",{"*":".^.c","flg":18},{"s":["^Mmm... I'm kinda cold.",{"->":"$r","var":true},null],"c":["ev",{"^->":"WATCHERS_BORED.0.9.c.14.g-0.4.c.$r2"},"/ev",{"temp=":"$r"},{"->":".^.^.s"},[{"#n":"$r2"}],"\n","\n",{"#":"w:right"},"\n","^Let's turn the heat up a bit then, you've got the air con turned all the way down!","\n",{"#":"w:right"},"\n","^Keep it like a freezer in here.","\n",{"->":".^.^.^.^.g-1"},{"#f":7}]}],["ev",{"^->":"WATCHERS_BORED.0.9.c.14.g-0.5.$r1"},{"temp=":"$r"},"str",{"->":".^.s"},[{"#n":"$r1"}],"/str","/ev",{"*":".^.c","flg":18},{"s":["^Mmm... I'm a bit warm.",{"->":"$r","var":true},null],"c":["ev",{"^->":"WATCHERS_BORED.0.9.c.14.g-0.5.c.$r2"},"/ev",{"temp=":"$r"},{"->":".^.^.s"},[{"#n":"$r2"}],"\n","\n",{"#":"w:right"},"\n","^Let's turn the air con up a bit then, you've got it all the way to the hot side.","\n",{"->":".^.^.^.^.g-1"},{"#f":7}]}],{"#f":7}],"g-1":[{"#":"w:left"},"\n","^Yeah, sorry.","\n",{"#":"w:right"},"\n","^What are you sorry about? Don't be silly.","\n",{"#":"w:right"},"\n","^I just mean like. Even though it kinda sucks it's at least nice to be out here in a place like this.","\n",{"#":"w:right"},"\n","^Y'know?","\n",{"#":"w:right"},"\n","^Like you never get to take in a place like this. Always passing through, never staying.","\n",{"#":"w:right"},"\n","^Would be a good location for a detective story or something.","\n",{"#":"w:left"},"\n","^Mmm.","\n",{"->":".^.^.^.^.^.g-0"},{"#f":7}]}],{"#f":7}]}],["ev",{"^->":"WATCHERS_BORED.0.10.$r1"},{"temp=":"$r"},"str",{"->":".^.s"},[{"#n":"$r1"}],"/str","/ev",{"*":".^.c","flg":18},{"s":["^I'm trying to watch it.",{"->":"$r","var":true},null],"c":["ev",{"^->":"WATCHERS_BORED.0.10.c.$r2"},"/ev",{"temp=":"$r"},{"->":".^.^.s"},[{"#n":"$r2"}],"\n","\n",{"#":"w:right"},"^Oh. Sorry. I'll be quiet.","\n",{"->":".^.^.^.g-0"},{"#f":7}]}],{"g-0":["done",{"#f":7}]}],{"#f":3}],"WATCHERS_WINDOW":[[{"#":"w:right"},"^I can't see anything out that window, it's too foggy.","\n",["ev",{"^->":"WATCHERS_WINDOW.0.3.$r1"},{"temp=":"$r"},"str",{"->":".^.s"},[{"#n":"$r1"}],"/str","/ev",{"*":".^.c","flg":18},{"s":["^Me either.",{"->":"$r","var":true},null],"c":["ev",{"^->":"WATCHERS_WINDOW.0.3.c.$r2"},"/ev",{"temp=":"$r"},{"->":".^.^.s"},[{"#n":"$r2"}],"\n","\n",{"->":".^.^.^.g-0"},{"#f":7}]}],["ev",{"^->":"WATCHERS_WINDOW.0.4.$r1"},{"temp=":"$r"},"str",{"->":".^.s"},[{"#n":"$r1"}],"/str","/ev",{"*":".^.c","flg":18},{"s":["^Yeah, it's creepy.",{"->":"$r","var":true},null],"c":["ev",{"^->":"WATCHERS_WINDOW.0.4.c.$r2"},"/ev",{"temp=":"$r"},{"->":".^.^.s"},[{"#n":"$r2"}],"\n","\n",{"->":".^.^.^.g-0"},{"#f":7}]}],{"g-0":[{"#":"w:right"},"^Like a room separate from reality.","\n","done",{"#f":7}]}],{"#f":3}],"WATCHERS_BATHROOM":[[{"#":"w:right"},"^I hate hotel bathrooms, they're so disgusting.","\n",["ev",{"^->":"WATCHERS_BATHROOM.0.3.$r1"},{"temp=":"$r"},"str",{"->":".^.s"},[{"#n":"$r1"}],"/str","/ev",{"*":".^.c","flg":18},{"s":["^Not the fancy ones.",{"->":"$r","var":true},null],"c":["ev",{"^->":"WATCHERS_BATHROOM.0.3.c.$r2"},"/ev",{"temp=":"$r"},{"->":".^.^.s"},[{"#n":"$r2"}],"\n","\n",{"#":"w:right"},"^No, no.","\n",{"->":".^.^.^.g-0"},{"#f":7}]}],["ev",{"^->":"WATCHERS_BATHROOM.0.4.$r1"},{"temp=":"$r"},"str",{"->":".^.s"},[{"#n":"$r1"}],"/str","/ev",{"*":".^.c","flg":18},{"s":["^I agree.",{"->":"$r","var":true},null],"c":["ev",{"^->":"WATCHERS_BATHROOM.0.4.c.$r2"},"/ev",{"temp=":"$r"},{"->":".^.^.s"},[{"#n":"$r2"}],"\n","\n",{"->":".^.^.^.g-0"},{"#f":7}]}],{"g-0":[{"#":"w:right"},"^Even the ones that pretend to be fancy have that same feel to them.","\n",{"#":"w:right"},"^That there's been hundreds of other people using it before you.","\n",{"#":"w:right"},"^No matter how well cleaned it still feels that way.","\n",{"#":"w:right"},"^Like sharing someone else's bar soap.","\n","done",{"#f":7}]}],{"#f":3}],"WATCHERS_BED":[[{"#":"w:right"},"^I can never dream in hotels.","\n",{"#":"w:right"},"^I can only dream when I'm at home.","\n",["ev",{"^->":"WATCHERS_BED.0.6.$r1"},{"temp=":"$r"},"str",{"->":".^.s"},[{"#n":"$r1"}],"/str","/ev",{"*":".^.c","flg":18},{"s":["^I'm the same.",{"->":"$r","var":true},null],"c":["ev",{"^->":"WATCHERS_BED.0.6.c.$r2"},"/ev",{"temp=":"$r"},{"->":".^.^.s"},[{"#n":"$r2"}],"\n","\n",{"#":"w:right"},"^When I move it takes me a while to start dreaming again, no matter where.","\n",{"#":"w:left"},"^Even in our new flat?","\n",{"#":"w:right"},"^Especially in our new flat.","\n",{"->":".^.^.^.g-0"},{"#f":7}]}],["ev",{"^->":"WATCHERS_BED.0.7.$r1"},{"temp=":"$r"},"str",{"->":".^.s"},[{"#n":"$r1"}],"/str","/ev",{"*":".^.c","flg":18},{"s":["^I always have nightmares.",{"->":"$r","var":true},null],"c":["ev",{"^->":"WATCHERS_BED.0.7.c.$r2"},"/ev",{"temp=":"$r"},{"->":".^.^.s"},[{"#n":"$r2"}],"\n","\n",{"#":"w:right"},"^Hotel nightmares?","\n",{"#":"w:left"},"^Yeah.","\n",{"#":"w:right"},"^I don't envy you.","\n",{"#":"w:left"},"^I don't wanna talk about it.","\n",{"->":".^.^.^.g-0"},{"#f":7}]}],{"g-0":["done",{"#f":7}]}],{"#f":3}],"WATCHERS_FIRST_LOOP":[[{"#":"w:right"},"^Wait what. Is it just looping now?","\n",{"#":"w:right"},"^Haven't we seen this bit before?","\n",["ev",{"^->":"WATCHERS_FIRST_LOOP.0.6.$r1"},{"temp=":"$r"},"str",{"->":".^.s"},[{"#n":"$r1"}],"/str","/ev",{"*":".^.c","flg":18},{"s":["^It looks like it.",{"->":"$r","var":true},null],"c":["ev",{"^->":"WATCHERS_FIRST_LOOP.0.6.c.$r2"},"/ev",{"temp=":"$r"},{"->":".^.^.s"},[{"#n":"$r2"}],"\n","\n",{"->":".^.^.^.g-0"},{"#f":7}]}],["ev",{"^->":"WATCHERS_FIRST_LOOP.0.7.$r1"},{"temp=":"$r"},"str",{"->":".^.s"},[{"#n":"$r1"}],"/str","/ev",{"*":".^.c","flg":18},{"s":["^No, it's a bit different I think.",{"->":"$r","var":true},null],"c":["ev",{"^->":"WATCHERS_FIRST_LOOP.0.7.c.$r2"},"/ev",{"temp=":"$r"},{"->":".^.^.s"},[{"#n":"$r2"}],"\n","\n",{"#":"w:right"},"^Is it?","\n",{"#":"w:left"},"^Yeah there's some little differences I think.","\n",{"->":".^.^.^.g-0"},{"#f":7}]}],["ev",{"^->":"WATCHERS_FIRST_LOOP.0.8.$r1"},{"temp=":"$r"},"str",{"->":".^.s"},[{"#n":"$r1"}],"/str","/ev",{"*":".^.c","flg":18},{"s":["^I can't tell.",{"->":"$r","var":true},null],"c":["ev",{"^->":"WATCHERS_FIRST_LOOP.0.8.c.$r2"},"/ev",{"temp=":"$r"},{"->":".^.^.s"},[{"#n":"$r2"}],"\n","\n",{"#":"w:right"},"^I feel like this is just the same as earlier.","\n",{"->":".^.^.^.g-0"},{"#f":7}]}],{"g-0":[{"#":"w:right"},"^Hmm.","\n",{"#":"w:right"},"^It's definitely the same room isn't it.","\n",{"#":"w:right"},"^But I can't tell if it's the same ghuest.","\n",{"#":"w:right"},"^They're doing pretty much the same things.","\n",{"#":"w:left"},"^Yeah.","\n",{"#":"w:right"},"^It's quite frustrating.","\n",{"#":"w:right"},"^It's a shame they can't hear us.","\n",{"#":"w:left"},"^Mmm.","\n","done",{"#f":7}]}],{"#f":3}],"WATCHERS_SECOND_LOOP":[[{"#":"w:right"},"^It feels like it's just gonna keep looping like this, doesn't it?","\n",["ev",{"^->":"WATCHERS_SECOND_LOOP.0.3.$r1"},{"temp=":"$r"},"str",{"->":".^.s"},[{"#n":"$r1"}],"/str","/ev",{"*":".^.c","flg":18},{"s":["^Yeah, it does.",{"->":"$r","var":true},null],"c":["ev",{"^->":"WATCHERS_SECOND_LOOP.0.3.c.$r2"},"/ev",{"temp=":"$r"},{"->":".^.^.s"},[{"#n":"$r2"}],"\n","\n",{"->":".^.^.^.g-0"},{"#f":7}]}],["ev",{"^->":"WATCHERS_SECOND_LOOP.0.4.$r1"},{"temp=":"$r"},"str",{"->":".^.s"},[{"#n":"$r1"}],"/str","/ev",{"*":".^.c","flg":18},{"s":["^What a weird film.",{"->":"$r","var":true},null],"c":["ev",{"^->":"WATCHERS_SECOND_LOOP.0.4.c.$r2"},"/ev",{"temp=":"$r"},{"->":".^.^.s"},[{"#n":"$r2"}],"\n","\n",{"->":".^.^.^.g-0"},{"#f":7}]}],{"g-0":[{"#":"w:right"},"^Can we go home now?","\n",{"#":"w:left"},"^Yeah sure.","\n",{"#":"w:right"},"^Thank you.","\n",{"#":"w:right"},"^Really can't wait to get back after watching this. See our bed and our furniture and everything again.","\n",{"#":"w:right"},"^You know what I mean?","\n",{"#":"w:left"},"^Yeah, weirdly homesick.","\n",{"#":"w:right"},"^Yeah, like. I don't know... Can't put my finger on it.","\n",["ev",{"^->":"WATCHERS_SECOND_LOOP.0.g-0.21.$r1"},{"temp=":"$r"},"str",{"->":".^.s"},[{"#n":"$r1"}],"/str","/ev",{"*":".^.c","flg":18},{"s":["^Yeah, something just feels really weird.",{"->":"$r","var":true},null],"c":["ev",{"^->":"WATCHERS_SECOND_LOOP.0.g-0.21.c.$r2"},"/ev",{"temp=":"$r"},{"->":".^.^.s"},[{"#n":"$r2"}],"\n","\n",{"->":".^.^.^.^.g-1"},{"#f":7}]}],["ev",{"^->":"WATCHERS_SECOND_LOOP.0.g-0.22.$r1"},{"temp=":"$r"},"str",{"->":".^.s"},[{"#n":"$r1"}],"/str","/ev",{"*":".^.c","flg":18},{"s":["^Yeah, I feel kinda uncomfortable.",{"->":"$r","var":true},null],"c":["ev",{"^->":"WATCHERS_SECOND_LOOP.0.g-0.22.c.$r2"},"/ev",{"temp=":"$r"},{"->":".^.^.s"},[{"#n":"$r2"}],"\n","\n",{"->":".^.^.^.^.g-1"},{"#f":7}]}],{"#f":7}],"g-1":[{"#":"w:left"},"^Like getting lost in a place I once knew.","\n",{"#":"w:right"},"^Yeah.","\n",{"#":"w:right"},"^When we get home can we have the rest of that pizza?","\n",["ev",{"^->":"WATCHERS_SECOND_LOOP.0.g-1.9.$r1"},{"temp=":"$r"},"str",{"->":".^.s"},[{"#n":"$r1"}],"/str","/ev",{"*":".^.c","flg":18},{"s":["^I thought you finished it earlier?",{"->":"$r","var":true},null],"c":["ev",{"^->":"WATCHERS_SECOND_LOOP.0.g-1.9.c.$r2"},"/ev",{"temp=":"$r"},{"->":".^.^.s"},[{"#n":"$r2"}],"\n","\n",{"->":".^.^.^.^.g-2"},{"#f":7}]}],["ev",{"^->":"WATCHERS_SECOND_LOOP.0.g-1.10.$r1"},{"temp=":"$r"},"str",{"->":".^.s"},[{"#n":"$r1"}],"/str","/ev",{"*":".^.c","flg":18},{"s":["^I'm not really in the mood anymore.",{"->":"$r","var":true},null],"c":["ev",{"^->":"WATCHERS_SECOND_LOOP.0.g-1.10.c.$r2"},"/ev",{"temp=":"$r"},{"->":".^.^.s"},[{"#n":"$r2"}],"\n","\n",{"->":".^.^.^.^.g-2"},{"#f":7}]}],{"#f":7}],"g-2":[["G>","ev","str","^TRIGGER_ENDING","/str",{"x()":"CustomEvent","exArgs":1},"out","/ev","G<",null],"\n","done",{"#f":7}]}],{"#f":3}],"#f":3}],"listDefs":{}}